README.rst
_description.org
lh-agpl3-LICENSE.txt
pyproject.toml
setup.py
bin/githubApiAccess.py
bin/githubApiReports.py
bisos/__init__.py
bisos.githubApi.egg-info/PKG-INFO
bisos.githubApi.egg-info/SOURCES.txt
bisos.githubApi.egg-info/dependency_links.txt
bisos.githubApi.egg-info/not-zip-safe
bisos.githubApi.egg-info/requires.txt
bisos.githubApi.egg-info/top_level.txt
bisos/githubApi/__init__.py
bisos/githubApi/githubApiLib.py